{
  "$schema": "https://developer.microsoft.com/json-schemas/fabric/item/report/definition/visualContainer/2.4.0/schema.json",
  "name": "3a1b678e0a6a354057a1",
  "position": {
    "x": 330.84708318950635,
    "y": 79.530548843631337,
    "z": 0,
    "height": 279.94753192958228,
    "width": 720.54677252329986,
    "tabOrder": 0
  },
  "visual": {
    "visualType": "cardVisual",
    "query": {
      "queryState": {
        "Data": {
          "projections": [
            {
              "field": {
                "Aggregation": {
                  "Expression": {
                    "Column": {
                      "Expression": {
                        "SourceRef": {
                          "Entity": "tbl_Refresh"
                        }
                      },
                      "Property": "FechaActualizacion"
                    }
                  },
                  "Function": 3
                }
              },
              "queryRef": "Min(tbl_Refresh.FechaActualizacion)",
              "nativeQueryRef": "Fecha de Actualización",
              "displayName": "Fecha de Actualización"
            }
          ]
        }
      },
      "sortDefinition": {
        "sort": [
          {
            "field": {
              "Aggregation": {
                "Expression": {
                  "Column": {
                    "Expression": {
                      "SourceRef": {
                        "Entity": "tbl_Refresh"
                      }
                    },
                    "Property": "FechaActualizacion"
                  }
                },
                "Function": 3
              }
            },
            "direction": "Ascending"
          }
        ],
        "isDefaultSort": true
      }
    },
    "objects": {
      "value": [
        {
          "properties": {
            "fontSize": {
              "expr": {
                "Literal": {
                  "Value": "44D"
                }
              }
            },
            "horizontalAlignment": {
              "expr": {
                "Literal": {
                  "Value": "'center'"
                }
              }
            }
          },
          "selector": {
            "id": "default"
          }
        }
      ],
      "label": [
        {
          "properties": {
            "fontSize": {
              "expr": {
                "Literal": {
                  "Value": "24D"
                }
              }
            }
          },
          "selector": {
            "id": "default"
          }
        }
      ],
      "layout": [
        {
          "properties": {
            "alignment": {
              "expr": {
                "Literal": {
                  "Value": "'middle'"
                }
              }
            }
          }
        }
      ]
    },
    "drillFilterOtherVisuals": true
  }
}